{
  "path": "./examples/live/",
  "name": "live",
  "children": [
    {
      "path": "examples/live/3d",
      "name": "3d",
      "children": [
        {
          "path": "examples/live/3d/edit cube.js",
          "name": "edit cube.js",
          "type": "file"
        },
        {
          "path": "examples/live/3d/primitives.js",
          "name": "primitives.js",
          "type": "file"
        },
        {
          "path": "examples/live/3d/rotating cube.js",
          "name": "rotating cube.js",
          "type": "file"
        }
      ],
      "type": "directory"
    },
    {
      "path": "examples/live/camera",
      "name": "camera",
      "children": [
        {
          "path": "examples/live/camera/bounds performance test.js",
          "name": "bounds performance test.js",
          "type": "file"
        },
        {
          "path": "examples/live/camera/performance test.js",
          "name": "performance test.js",
          "type": "file"
        }
      ],
      "type": "directory"
    },
    {
      "path": "examples/live/direct mode",
      "name": "direct mode",
      "children": [
        {
          "path": "examples/live/direct mode/draw frame.js",
          "name": "draw frame.js",
          "type": "file"
        },
        {
          "path": "examples/live/direct mode/draw image part.js",
          "name": "draw image part.js",
          "type": "file"
        },
        {
          "path": "examples/live/direct mode/draw image.js",
          "name": "draw image.js",
          "type": "file"
        },
        {
          "path": "examples/live/direct mode/draw image.min.js",
          "name": "draw image.min.js",
          "type": "file"
        },
        {
          "path": "examples/live/direct mode/draw quad.js",
          "name": "draw quad.js",
          "type": "file"
        },
        {
          "path": "examples/live/direct mode/draw scaled frame.js",
          "name": "draw scaled frame.js",
          "type": "file"
        },
        {
          "path": "examples/live/direct mode/draw scaled image.js",
          "name": "draw scaled image.js",
          "type": "file"
        },
        {
          "path": "examples/live/direct mode/draw tiles.js",
          "name": "draw tiles.js",
          "type": "file"
        },
        {
          "path": "examples/live/direct mode/fill line.js",
          "name": "fill line.js",
          "type": "file"
        },
        {
          "path": "examples/live/direct mode/fill lots of rects.js",
          "name": "fill lots of rects.js",
          "type": "file"
        },
        {
          "path": "examples/live/direct mode/fill rect.js",
          "name": "fill rect.js",
          "type": "file"
        },
        {
          "path": "examples/live/direct mode/fill triangle.js",
          "name": "fill triangle.js",
          "type": "file"
        },
        {
          "path": "examples/live/direct mode/no scene await.js",
          "name": "no scene await.js",
          "type": "file"
        },
        {
          "path": "examples/live/direct mode/no scene.js",
          "name": "no scene.js",
          "type": "file"
        }
      ],
      "type": "directory"
    },
    {
      "path": "examples/live/display",
      "name": "display",
      "children": [
        {
          "path": "examples/live/display/add child on click.js",
          "name": "add child on click.js",
          "type": "file"
        },
        {
          "path": "examples/live/display/add child to parent on click.js",
          "name": "add child to parent on click.js",
          "type": "file"
        },
        {
          "path": "examples/live/display/add child.js",
          "name": "add child.js",
          "type": "file"
        },
        {
          "path": "examples/live/display/add children.js",
          "name": "add children.js",
          "type": "file"
        },
        {
          "path": "examples/live/display/add over time.js",
          "name": "add over time.js",
          "type": "file"
        },
        {
          "path": "examples/live/display/call add child multiple times.js",
          "name": "call add child multiple times.js",
          "type": "file"
        },
        {
          "path": "examples/live/display/display debug tools.js",
          "name": "display debug tools.js",
          "type": "file"
        },
        {
          "path": "examples/live/display/mass child test.js",
          "name": "mass child test.js",
          "type": "file"
        },
        {
          "path": "examples/live/display/mass draw test.js",
          "name": "mass draw test.js",
          "type": "file"
        }
      ],
      "type": "directory"
    },
    {
      "path": "examples/live/effects",
      "name": "effects",
      "children": [
        {
          "path": "examples/live/effects/matrix effects 1.js",
          "name": "matrix effects 1.js",
          "type": "file"
        },
        {
          "path": "examples/live/effects/matrix effects 2.js",
          "name": "matrix effects 2.js",
          "type": "file"
        },
        {
          "path": "examples/live/effects/matrix effects 3.js",
          "name": "matrix effects 3.js",
          "type": "file"
        },
        {
          "path": "examples/live/effects/matrix effects 4.js",
          "name": "matrix effects 4.js",
          "type": "file"
        },
        {
          "path": "examples/live/effects/matrix effects 5.js",
          "name": "matrix effects 5.js",
          "type": "file"
        },
        {
          "path": "examples/live/effects/matrix effects 6.js",
          "name": "matrix effects 6.js",
          "type": "file"
        },
        {
          "path": "examples/live/effects/matrix effects 7.js",
          "name": "matrix effects 7.js",
          "type": "file"
        },
        {
          "path": "examples/live/effects/world color.js",
          "name": "world color.js",
          "type": "file"
        }
      ],
      "type": "directory"
    },
    {
      "path": "examples/live/gameobjects",
      "name": "gameobjects",
      "children": [
        {
          "path": "examples/live/gameobjects/animatedsprite",
          "name": "animatedsprite",
          "children": [
            {
              "path": "examples/live/gameobjects/animatedsprite/atlas animation.js",
              "name": "atlas animation.js",
              "type": "file"
            },
            {
              "path": "examples/live/gameobjects/animatedsprite/create animation from atlas.js",
              "name": "create animation from atlas.js",
              "type": "file"
            }
          ],
          "type": "directory"
        },
        {
          "path": "examples/live/gameobjects/container",
          "name": "container",
          "children": [
            {
              "path": "examples/live/gameobjects/container/add children.js",
              "name": "add children.js",
              "type": "file"
            },
            {
              "path": "examples/live/gameobjects/container/banshee.js",
              "name": "banshee.js",
              "type": "file"
            }
          ],
          "type": "directory"
        },
        {
          "path": "examples/live/gameobjects/directdraw",
          "name": "directdraw",
          "children": [
            {
              "path": "examples/live/gameobjects/directdraw/circle.js",
              "name": "circle.js",
              "type": "file"
            },
            {
              "path": "examples/live/gameobjects/directdraw/circle.min.js",
              "name": "circle.min.js",
              "type": "file"
            },
            {
              "path": "examples/live/gameobjects/directdraw/draw rect.js",
              "name": "draw rect.js",
              "type": "file"
            },
            {
              "path": "examples/live/gameobjects/directdraw/layered drawing.js",
              "name": "layered drawing.js",
              "type": "file"
            },
            {
              "path": "examples/live/gameobjects/directdraw/multiple circles.js",
              "name": "multiple circles.js",
              "type": "file"
            },
            {
              "path": "examples/live/gameobjects/directdraw/plot.js",
              "name": "plot.js",
              "type": "file"
            },
            {
              "path": "examples/live/gameobjects/directdraw/shapes.js",
              "name": "shapes.js",
              "type": "file"
            },
            {
              "path": "examples/live/gameobjects/directdraw/sprite bounds.js",
              "name": "sprite bounds.js",
              "type": "file"
            },
            {
              "path": "examples/live/gameobjects/directdraw/tiles.js",
              "name": "tiles.js",
              "type": "file"
            },
            {
              "path": "examples/live/gameobjects/directdraw/trail.js",
              "name": "trail.js",
              "type": "file"
            }
          ],
          "type": "directory"
        },
        {
          "path": "examples/live/gameobjects/effectlayer",
          "name": "effectlayer",
          "children": [
            {
              "path": "examples/live/gameobjects/effectlayer/blur layer.js",
              "name": "blur layer.js",
              "type": "file"
            },
            {
              "path": "examples/live/gameobjects/effectlayer/camera effect layer.js",
              "name": "camera effect layer.js",
              "type": "file"
            },
            {
              "path": "examples/live/gameobjects/effectlayer/checkerboard.js",
              "name": "checkerboard.js",
              "type": "file"
            },
            {
              "path": "examples/live/gameobjects/effectlayer/create effect layer.js",
              "name": "create effect layer.js",
              "type": "file"
            },
            {
              "path": "examples/live/gameobjects/effectlayer/effect layer with sampler2d.js",
              "name": "effect layer with sampler2d.js",
              "type": "file"
            },
            {
              "path": "examples/live/gameobjects/effectlayer/full screen fx.js",
              "name": "full screen fx.js",
              "type": "file"
            },
            {
              "path": "examples/live/gameobjects/effectlayer/gradient.js",
              "name": "gradient.js",
              "type": "file"
            },
            {
              "path": "examples/live/gameobjects/effectlayer/rectangle effect layer.js",
              "name": "rectangle effect layer.js",
              "type": "file"
            }
          ],
          "type": "directory"
        },
        {
          "path": "examples/live/gameobjects/layer",
          "name": "layer",
          "children": [
            {
              "path": "examples/live/gameobjects/layer/create layer.js",
              "name": "create layer.js",
              "type": "file"
            }
          ],
          "type": "directory"
        },
        {
          "path": "examples/live/gameobjects/rectangle",
          "name": "rectangle",
          "children": [
            {
              "path": "examples/live/gameobjects/rectangle/1024 rectangles.js",
              "name": "1024 rectangles.js",
              "type": "file"
            },
            {
              "path": "examples/live/gameobjects/rectangle/create rectangle.js",
              "name": "create rectangle.js",
              "type": "file"
            },
            {
              "path": "examples/live/gameobjects/rectangle/random rectangles.js",
              "name": "random rectangles.js",
              "type": "file"
            },
            {
              "path": "examples/live/gameobjects/rectangle/transforming rectangles.js",
              "name": "transforming rectangles.js",
              "type": "file"
            }
          ],
          "type": "directory"
        },
        {
          "path": "examples/live/gameobjects/renderlayer",
          "name": "renderlayer",
          "children": [
            {
              "path": "examples/live/gameobjects/renderlayer/camera render layer.js",
              "name": "camera render layer.js",
              "type": "file"
            },
            {
              "path": "examples/live/gameobjects/renderlayer/create render layer.js",
              "name": "create render layer.js",
              "type": "file"
            },
            {
              "path": "examples/live/gameobjects/renderlayer/render layer with color matrix.js",
              "name": "render layer with color matrix.js",
              "type": "file"
            }
          ],
          "type": "directory"
        },
        {
          "path": "examples/live/gameobjects/sprite",
          "name": "sprite",
          "children": [
            {
              "path": "examples/live/gameobjects/sprite/add sprite on click.js",
              "name": "add sprite on click.js",
              "type": "file"
            },
            {
              "path": "examples/live/gameobjects/sprite/bounce sprite.js",
              "name": "bounce sprite.js",
              "type": "file"
            },
            {
              "path": "examples/live/gameobjects/sprite/create sprite.js",
              "name": "create sprite.js",
              "type": "file"
            },
            {
              "path": "examples/live/gameobjects/sprite/debug sprite.js",
              "name": "debug sprite.js",
              "type": "file"
            },
            {
              "path": "examples/live/gameobjects/sprite/lots of sprites.js",
              "name": "lots of sprites.js",
              "type": "file"
            },
            {
              "path": "examples/live/gameobjects/sprite/mass sprite ecs.js",
              "name": "mass sprite ecs.js",
              "type": "file"
            },
            {
              "path": "examples/live/gameobjects/sprite/rotating sprite.js",
              "name": "rotating sprite.js",
              "type": "file"
            },
            {
              "path": "examples/live/gameobjects/sprite/sprite prerender.js",
              "name": "sprite prerender.js",
              "type": "file"
            }
          ],
          "type": "directory"
        },
        {
          "path": "examples/live/gameobjects/text",
          "name": "text",
          "children": [
            {
              "path": "examples/live/gameobjects/text/create text.js",
              "name": "create text.js",
              "type": "file"
            },
            {
              "path": "examples/live/gameobjects/text/fill style.js",
              "name": "fill style.js",
              "type": "file"
            },
            {
              "path": "examples/live/gameobjects/text/text stroke.js",
              "name": "text stroke.js",
              "type": "file"
            },
            {
              "path": "examples/live/gameobjects/text/update text.js",
              "name": "update text.js",
              "type": "file"
            }
          ],
          "type": "directory"
        }
      ],
      "type": "directory"
    },
    {
      "path": "examples/live/input",
      "name": "input",
      "children": [
        {
          "path": "examples/live/input/keyboard",
          "name": "keyboard",
          "children": [
            {
              "path": "examples/live/input/keyboard/keydown.js",
              "name": "keydown.js",
              "type": "file"
            },
            {
              "path": "examples/live/input/keyboard/left and right.js",
              "name": "left and right.js",
              "type": "file"
            }
          ],
          "type": "directory"
        }
      ],
      "type": "directory"
    },
    {
      "path": "examples/live/loader",
      "name": "loader",
      "children": [
        {
          "path": "examples/live/loader/async start.js",
          "name": "async start.js",
          "type": "file"
        },
        {
          "path": "examples/live/loader/atlas.js",
          "name": "atlas.js",
          "type": "file"
        },
        {
          "path": "examples/live/loader/binary.js",
          "name": "binary.js",
          "type": "file"
        },
        {
          "path": "examples/live/loader/csv.js",
          "name": "csv.js",
          "type": "file"
        },
        {
          "path": "examples/live/loader/image.js",
          "name": "image.js",
          "type": "file"
        },
        {
          "path": "examples/live/loader/imageobject.js",
          "name": "imageobject.js",
          "type": "file"
        },
        {
          "path": "examples/live/loader/json.js",
          "name": "json.js",
          "type": "file"
        },
        {
          "path": "examples/live/loader/spritesheet.js",
          "name": "spritesheet.js",
          "type": "file"
        }
      ],
      "type": "directory"
    },
    {
      "path": "examples/live/test",
      "name": "test",
      "children": [
        {
          "path": "examples/live/test/grid.js",
          "name": "grid.js",
          "type": "file"
        },
        {
          "path": "examples/live/test/hash.js",
          "name": "hash.js",
          "type": "file"
        }
      ],
      "type": "directory"
    },
    {
      "path": "examples/live/textures",
      "name": "textures",
      "children": [
        {
          "path": "examples/live/textures/compressed texture atlas.js",
          "name": "compressed texture atlas.js",
          "type": "file"
        },
        {
          "path": "examples/live/textures/compressed textures.js",
          "name": "compressed textures.js",
          "type": "file"
        },
        {
          "path": "examples/live/textures/flame shader.js",
          "name": "flame shader.js",
          "type": "file"
        },
        {
          "path": "examples/live/textures/linear gradient texture 1.js",
          "name": "linear gradient texture 1.js",
          "type": "file"
        },
        {
          "path": "examples/live/textures/linear gradient texture 2.js",
          "name": "linear gradient texture 2.js",
          "type": "file"
        },
        {
          "path": "examples/live/textures/linear gradient texture 3.js",
          "name": "linear gradient texture 3.js",
          "type": "file"
        },
        {
          "path": "examples/live/textures/max texture units.js",
          "name": "max texture units.js",
          "type": "file"
        },
        {
          "path": "examples/live/textures/pixel texture 1.js",
          "name": "pixel texture 1.js",
          "type": "file"
        },
        {
          "path": "examples/live/textures/set max textures 1.js",
          "name": "set max textures 1.js",
          "type": "file"
        },
        {
          "path": "examples/live/textures/shader texture.js",
          "name": "shader texture.js",
          "type": "file"
        },
        {
          "path": "examples/live/textures/texture atlas.js",
          "name": "texture atlas.js",
          "type": "file"
        },
        {
          "path": "examples/live/textures/trimmed texture atlas.js",
          "name": "trimmed texture atlas.js",
          "type": "file"
        }
      ],
      "type": "directory"
    }
  ],
  "type": "directory"
}